{
  "version": "7",
  "dialect": "postgresql",
  "entries": [
    {
      "idx": 0,
      "version": "7",
      "when": 1781178073233,
      "tag": "0000_rapid_black_tarantula",
      "breakpoints": true
    },
    {
      "idx": 1,
      "version": "7",
      "when": 1781228193096,
      "tag": "0001_outgoing_matthew_murdock",
      "breakpoints": true
    },
    {
      "idx": 2,
      "version": "7",
      "when": 1781228841614,
      "tag": "0002_modern_zeigeist",
      "breakpoints": true
    },
    {
      "idx": 3,
      "version": "7",
      "when": 1781328841614,
      "tag": "0003_steep_redwing",
      "breakpoints": true
    },
    {
      "idx": 4,
      "version": "7",
      "when": 1781428841614,
      "tag": "0004_mixed_northstar",
      "breakpoints": true
    },
    {
      "idx": 5,
      "version": "7",
      "when": 1781528841614,
      "tag": "0005_sudden_blazing_skull",
      "breakpoints": true
    }
  ]
}